README.txt
setup.cfg
setup.py
docs/CHANGES.txt
docs/INSTALL.txt
docs/LICENSE.GPL
docs/LICENSE.txt
unweb/__init__.py
unweb.shareit.egg-info/PKG-INFO
unweb.shareit.egg-info/SOURCES.txt
unweb.shareit.egg-info/dependency_links.txt
unweb.shareit.egg-info/entry_points.txt
unweb.shareit.egg-info/namespace_packages.txt
unweb.shareit.egg-info/not-zip-safe
unweb.shareit.egg-info/paster_plugins.txt
unweb.shareit.egg-info/requires.txt
unweb.shareit.egg-info/top_level.txt
unweb/shareit/__init__.py
unweb/shareit/configure.zcml
unweb/shareit/interfaces.py
unweb/shareit/tests.py
unweb/shareit/browser/__init__.py
unweb/shareit/browser/configure.zcml
unweb/shareit/browser/interfaces.py
unweb/shareit/browser/views.py
unweb/shareit/browser/css/shareit.css
unweb/shareit/browser/images/delicious.gif
unweb/shareit/browser/images/digg.gif
unweb/shareit/browser/images/facebook.png
unweb/shareit/browser/images/iwiw.png
unweb/shareit/browser/images/orkut.png
unweb/shareit/browser/images/share_icon.gif
unweb/shareit/browser/images/twitter.gif.ico
unweb/shareit/browser/templates/jquery.shareit.js
unweb/shareit/browser/templates/share.pt
unweb/shareit/profiles/default/actions.xml
unweb/shareit/profiles/default/cssregistry.xml
unweb/shareit/profiles/default/jsregistry.xml