Metadata-Version: 1.0
Name: unweb.shareit
Version: 0.1
Summary: Adds a jquery share content popup in document actions
Home-page: http://svn.plone.org/svn/collective/
Author: UNKNOWN
Author-email: UNKNOWN
License: GPL
Platform: UNKNOWN
Classifier: Framework :: Plone
Classifier: Programming Language :: Python
